gxipy/DataStream.py
gxipy/Device.py
gxipy/DeviceManager.py
gxipy/Exception.py
gxipy/Feature.py
gxipy/FeatureControl.py
gxipy/Feature_s.py
gxipy/ImageFormatConvert.py
gxipy/ImageProc.py
gxipy/ImageProcess.py
gxipy/ImageProcessConfig.py
gxipy/Interface.py
gxipy/StatusProcessor.py
gxipy/__init__.py
gxipy/dxwrapper.py
gxipy/gxiapi.py
gxipy/gxidef.py
gxipy/gxwrapper.py
open_gxipy-2.0.2403.9191.dist-info/LICENSE
open_gxipy-2.0.2403.9191.dist-info/METADATA
open_gxipy-2.0.2403.9191.dist-info/WHEEL
open_gxipy-2.0.2403.9191.dist-info/top_level.txt
open_gxipy-2.0.2403.9191.dist-info/RECORD
