Metadata-Version: 2.1
Name: open-gxipy
Version: 2.0.2403.9191
Summary: Python API to use with the HS Soft cameras.
Home-page: https://github.com/otabek-olimjonov/open_gxipy
Author: HS Soft
License: MIT
Classifier: Programming Language :: Python :: 3
Classifier: License :: OSI Approved :: MIT License
Classifier: Operating System :: OS Independent
License-File: LICENSE
Requires-Dist: numpy
Requires-Dist: Pillow
